<?xml version='1.0' encoding='UTF-8'?>
<quiz><question type="multichoice"><name><text>Ujian Materi DKS 19 November 2021</text></name><questiontext format="html"><text><![CDATA[<p>Untuk mengetahui adanya gangguan di organ pancreas ada beberapa indikator yang harus dinilai dari pemeriksaan darah antara lain</p>]]></text></questiontext><generalfeedback format="html"><text/></generalfeedback><defaultgrade>1</defaultgrade><penalty>0</penalty><hidden>0</hidden><idnumber>QST_154518</idnumber><single>true</single><answernumbering>abc</answernumbering><showstandardinstruction>0</showstandardinstruction><correctfeedback format="html"><text><![CDATA[<p>Your answer is correct.</p>]]></text></correctfeedback><partiallycorrectfeedback format="html"><text><![CDATA[<p>Your answer is partially correct.</p>]]></text></partiallycorrectfeedback><incorrectfeedback format="html"><text><![CDATA[<p>Your answer is incorrect.</p>]]></text></incorrectfeedback><shownumcorrect/><answer fraction="0.0" format="html"><text><![CDATA[<p>Enzim lipase</p>]]></text><feedback><text/></feedback></answer><answer fraction="0.0" format="html"><text><![CDATA[<p>enzim amilase</p>]]></text><feedback><text/></feedback></answer><answer fraction="50.0" format="html"><text><![CDATA[<p>Enzim lipase dan amilase</p>]]></text><feedback><text/></feedback></answer><answer fraction="0.0" format="html"><text><![CDATA[<p>Enzim katalase</p>]]></text><feedback><text/></feedback></answer></question><question type="multichoice"><name><text>Ujian Materi DKS 19 November 2021</text></name><questiontext format="html"><text><![CDATA[<p>Semua enzim yang terdeteksi di serum dalam kondisi level minimum sehingga pemeriksaan harus dilakukan</p>]]></text></questiontext><generalfeedback format="html"><text/></generalfeedback><defaultgrade>1</defaultgrade><penalty>0</penalty><hidden>0</hidden><idnumber>QST_154519</idnumber><single>true</single><answernumbering>abc</answernumbering><showstandardinstruction>0</showstandardinstruction><correctfeedback format="html"><text><![CDATA[<p>Your answer is correct.</p>]]></text></correctfeedback><partiallycorrectfeedback format="html"><text><![CDATA[<p>Your answer is partially correct.</p>]]></text></partiallycorrectfeedback><incorrectfeedback format="html"><text><![CDATA[<p>Your answer is incorrect.</p>]]></text></incorrectfeedback><shownumcorrect/><answer fraction="0.0" format="html"><text><![CDATA[<p>Kurang dari 24 jam</p>]]></text><feedback><text/></feedback></answer><answer fraction="0.0" format="html"><text><![CDATA[<p>Lewat dari 24 jam</p>]]></text><feedback><text/></feedback></answer><answer fraction="50.0" format="html"><text><![CDATA[<p>Secepatnya dilakukan pemeriksaan</p>]]></text><feedback><text/></feedback></answer><answer fraction="0.0" format="html"><text><![CDATA[<p>Setelah 1 minggu</p>]]></text><feedback><text/></feedback></answer></question><question type="multichoice"><name><text>Ujian Materi DKS 19 November 2021</text></name><questiontext format="html"><text><![CDATA[<p>Kondisi pankreatitis akut sebaiknya dilakukan pemeriksaan dengan mengambil sampel</p>]]></text></questiontext><generalfeedback format="html"><text/></generalfeedback><defaultgrade>1</defaultgrade><penalty>0</penalty><hidden>0</hidden><idnumber>QST_154521</idnumber><single>true</single><answernumbering>abc</answernumbering><showstandardinstruction>0</showstandardinstruction><correctfeedback format="html"><text><![CDATA[<p>Your answer is correct.</p>]]></text></correctfeedback><partiallycorrectfeedback format="html"><text><![CDATA[<p>Your answer is partially correct.</p>]]></text></partiallycorrectfeedback><incorrectfeedback format="html"><text><![CDATA[<p>Your answer is incorrect.</p>]]></text></incorrectfeedback><shownumcorrect/><answer fraction="50.0" format="html"><text><![CDATA[<p>darah</p>]]></text><feedback><text/></feedback></answer><answer fraction="0.0" format="html"><text><![CDATA[<p>urin</p>]]></text><feedback><text/></feedback></answer><answer fraction="0.0" format="html"><text><![CDATA[<p>feses</p>]]></text><feedback><text/></feedback></answer><answer fraction="0.0" format="html"><text><![CDATA[<p>cairan tubuh</p>]]></text><feedback><text/></feedback></answer></question><question type="multichoice"><name><text>Ujian Materi DKS 19 November 2021</text></name><questiontext format="html"><text><![CDATA[<p>Kondisi pankreatitis kronis sebaiknya dilakukan pemeriksaan dengan mengambil sampel</p>]]></text></questiontext><generalfeedback format="html"><text/></generalfeedback><defaultgrade>1</defaultgrade><penalty>0</penalty><hidden>0</hidden><idnumber>QST_154522</idnumber><single>true</single><answernumbering>abc</answernumbering><showstandardinstruction>0</showstandardinstruction><correctfeedback format="html"><text><![CDATA[<p>Your answer is correct.</p>]]></text></correctfeedback><partiallycorrectfeedback format="html"><text><![CDATA[<p>Your answer is partially correct.</p>]]></text></partiallycorrectfeedback><incorrectfeedback format="html"><text><![CDATA[<p>Your answer is incorrect.</p>]]></text></incorrectfeedback><shownumcorrect/><answer fraction="0.0" format="html"><text><![CDATA[<p>darah</p>]]></text><feedback><text/></feedback></answer><answer fraction="0.0" format="html"><text><![CDATA[<p>urin</p>]]></text><feedback><text/></feedback></answer><answer fraction="50.0" format="html"><text><![CDATA[<p>feses</p>]]></text><feedback><text/></feedback></answer><answer fraction="0.0" format="html"><text><![CDATA[<p>cairan tubuh</p>]]></text><feedback><text/></feedback></answer></question><question type="multichoice"><name><text>Ujian Materi DKS 19 November 2021</text></name><questiontext format="html"><text><![CDATA[<p>Untuk pemeriksaan penyakit pancreas dilakukan dengan memeriksa primary pancreatic panel yang terdiri dari</p>]]></text></questiontext><generalfeedback format="html"><text/></generalfeedback><defaultgrade>1</defaultgrade><penalty>0</penalty><hidden>0</hidden><idnumber>QST_154533</idnumber><single>true</single><answernumbering>abc</answernumbering><showstandardinstruction>0</showstandardinstruction><correctfeedback format="html"><text><![CDATA[<p>Your answer is correct.</p>]]></text></correctfeedback><partiallycorrectfeedback format="html"><text><![CDATA[<p>Your answer is partially correct.</p>]]></text></partiallycorrectfeedback><incorrectfeedback format="html"><text><![CDATA[<p>Your answer is incorrect.</p>]]></text></incorrectfeedback><shownumcorrect/><answer fraction="50.0" format="html"><text><![CDATA[<p>lipase, amilase, BUN</p>]]></text><feedback><text/></feedback></answer><answer fraction="0.0" format="html"><text><![CDATA[<p>creatinin, lipase, cholesterol</p>]]></text><feedback><text/></feedback></answer><answer fraction="0.0" format="html"><text><![CDATA[<p>lipase, milase, cholesterol</p>]]></text><feedback><text/></feedback></answer><answer fraction="0.0" format="html"><text><![CDATA[<p>calcium, albumin, ALT, ALP, Glukosa, cholesterol</p>]]></text><feedback><text/></feedback></answer></question><question type="multichoice"><name><text>Ujian Materi DKS 19 November 2021</text></name><questiontext format="html"><text><![CDATA[<p>Untuk pemeriksaan penyakit pancreas dilakukan dengan memeriksa secondary pancreatic panel yang terdiri dari</p>]]></text></questiontext><generalfeedback format="html"><text/></generalfeedback><defaultgrade>1</defaultgrade><penalty>0</penalty><hidden>0</hidden><idnumber>QST_154535</idnumber><single>true</single><answernumbering>abc</answernumbering><showstandardinstruction>0</showstandardinstruction><correctfeedback format="html"><text><![CDATA[<p>Your answer is correct.</p>]]></text></correctfeedback><partiallycorrectfeedback format="html"><text><![CDATA[<p>Your answer is partially correct.</p>]]></text></partiallycorrectfeedback><incorrectfeedback format="html"><text><![CDATA[<p>Your answer is incorrect.</p>]]></text></incorrectfeedback><shownumcorrect/><answer fraction="0.0" format="html"><text><![CDATA[<p>cratinin, lipase, cholesterol</p>]]></text><feedback><text/></feedback></answer><answer fraction="0.0" format="html"><text><![CDATA[<p>lipase, amilase, cholesterol</p>]]></text><feedback><text/></feedback></answer><answer fraction="0.0" format="html"><text><![CDATA[<p>amilase, lipase, BUN</p>]]></text><feedback><text/></feedback></answer><answer fraction="100.0" format="html"><text><![CDATA[<p>calcium, albumin, ALT, ALP, Glukosa, Cholesterol</p>]]></text><feedback><text/></feedback></answer></question><question type="multichoice"><name><text>Ujian Materi DKS 19 November 2021</text></name><questiontext format="html"><text><![CDATA[<p>Pada kondisi gangguan pankreas terjadi peningkatan amylase, enzim ini juga meningkat pada</p>]]></text></questiontext><generalfeedback format="html"><text/></generalfeedback><defaultgrade>1</defaultgrade><penalty>0</penalty><hidden>0</hidden><idnumber>QST_154578</idnumber><single>true</single><answernumbering>abc</answernumbering><showstandardinstruction>0</showstandardinstruction><correctfeedback format="html"><text><![CDATA[<p>Your answer is correct.</p>]]></text></correctfeedback><partiallycorrectfeedback format="html"><text><![CDATA[<p>Your answer is partially correct.</p>]]></text></partiallycorrectfeedback><incorrectfeedback format="html"><text><![CDATA[<p>Your answer is incorrect.</p>]]></text></incorrectfeedback><shownumcorrect/><answer fraction="0.0" format="html"><text><![CDATA[<p>gangguan fungsi hati dan lambung</p>]]></text><feedback><text/></feedback></answer><answer fraction="100.0" format="html"><text><![CDATA[<p>gangguan fungsi ginjal atau usus</p>]]></text><feedback><text/></feedback></answer><answer fraction="0.0" format="html"><text><![CDATA[<p>gangguan fungsi usus atau lambung</p>]]></text><feedback><text/></feedback></answer><answer fraction="0.0" format="html"><text><![CDATA[<p>gangguan fungsi hati</p>]]></text><feedback><text/></feedback></answer></question><question type="multichoice"><name><text>Ujian Materi DKS 19 November 2021</text></name><questiontext format="html"><text><![CDATA[<p>Kondisi yang sering bias dengan adanya peningkatan hingga 5 x enzim lipase tapi tidak ada peningkatan amylase tidak dapat dikategorikan sebagai pancreatitis akut, tapi kondisi tersebut bisa terjadi akibat</p>]]></text></questiontext><generalfeedback format="html"><text/></generalfeedback><defaultgrade>1</defaultgrade><penalty>0</penalty><hidden>0</hidden><idnumber>QST_154581</idnumber><single>true</single><answernumbering>abc</answernumbering><showstandardinstruction>0</showstandardinstruction><correctfeedback format="html"><text><![CDATA[<p>Your answer is correct.</p>]]></text></correctfeedback><partiallycorrectfeedback format="html"><text><![CDATA[<p>Your answer is partially correct.</p>]]></text></partiallycorrectfeedback><incorrectfeedback format="html"><text><![CDATA[<p>Your answer is incorrect.</p>]]></text></incorrectfeedback><shownumcorrect/><answer fraction="100.0" format="html"><text><![CDATA[<p>penggunaan dexametasone</p>]]></text><feedback><text/></feedback></answer><answer fraction="0.0" format="html"><text><![CDATA[<p>pemberian hormon steroid</p>]]></text><feedback><text/></feedback></answer><answer fraction="0.0" format="html"><text><![CDATA[<p>pemberian diet gula yang berlebihan</p>]]></text><feedback><text/></feedback></answer><answer fraction="0.0" format="html"><text><![CDATA[<p>pemberian hormon non steroid</p>]]></text><feedback><text/></feedback></answer></question><question type="multichoice"><name><text>Ujian Materi DKS 19 November 2021</text></name><questiontext format="html"><text><![CDATA[<p>50% kondisi pancreatitis akut terjadi juga kondisi</p>]]></text></questiontext><generalfeedback format="html"><text/></generalfeedback><defaultgrade>1</defaultgrade><penalty>0</penalty><hidden>0</hidden><idnumber>QST_154672</idnumber><single>true</single><answernumbering>abc</answernumbering><showstandardinstruction>0</showstandardinstruction><correctfeedback format="html"><text><![CDATA[<p>Your answer is correct.</p>]]></text></correctfeedback><partiallycorrectfeedback format="html"><text><![CDATA[<p>Your answer is partially correct.</p>]]></text></partiallycorrectfeedback><incorrectfeedback format="html"><text><![CDATA[<p>Your answer is incorrect.</p>]]></text></incorrectfeedback><shownumcorrect/><answer fraction="50.0" format="html"><text><![CDATA[<p>hipokalsemia</p>]]></text><feedback><text/></feedback></answer><answer fraction="0.0" format="html"><text><![CDATA[<p>hipoglikemia</p>]]></text><feedback><text/></feedback></answer><answer fraction="0.0" format="html"><text><![CDATA[<p>osteomalasia</p>]]></text><feedback><text/></feedback></answer><answer fraction="0.0" format="html"><text><![CDATA[<p>rachitis</p>]]></text><feedback><text/></feedback></answer></question><question type="multichoice"><name><text>Ujian Materi DKS 19 November 2021</text></name><questiontext format="html"><text><![CDATA[<p>Pemeriksaan pankreatitis secara umum dengan melihat panel primer hanya sekitar 50% keakuratannya pada anjing, sehingga dibutuhkan pemeriksaan lebih lanjut yang spesifik yaitu</p>]]></text></questiontext><generalfeedback format="html"><text/></generalfeedback><defaultgrade>1</defaultgrade><penalty>0</penalty><hidden>0</hidden><idnumber>QST_154673</idnumber><single>true</single><answernumbering>abc</answernumbering><showstandardinstruction>0</showstandardinstruction><correctfeedback format="html"><text><![CDATA[<p>Your answer is correct.</p>]]></text></correctfeedback><partiallycorrectfeedback format="html"><text><![CDATA[<p>Your answer is partially correct.</p>]]></text></partiallycorrectfeedback><incorrectfeedback format="html"><text><![CDATA[<p>Your answer is incorrect.</p>]]></text></incorrectfeedback><shownumcorrect/><answer fraction="50.0" format="html"><text><![CDATA[<p>Serum TLI</p>]]></text><feedback><text/></feedback></answer><answer fraction="0.0" format="html"><text><![CDATA[<p>Serum cPLI</p>]]></text><feedback><text/></feedback></answer><answer fraction="0.0" format="html"><text><![CDATA[<p>Abnormal ultrasound</p>]]></text><feedback><text/></feedback></answer><answer fraction="0.0" format="html"><text><![CDATA[<p>Fecal test</p>]]></text><feedback><text/></feedback></answer></question><question type="multichoice"><name><text>Ujian Materi DKS 19 November 2021</text></name><questiontext format="html"><text><![CDATA[<p>Marker pemeriksaan untuk otot</p>]]></text></questiontext><generalfeedback format="html"><text/></generalfeedback><defaultgrade>1</defaultgrade><penalty>0</penalty><hidden>0</hidden><idnumber>QST_154675</idnumber><single>true</single><answernumbering>abc</answernumbering><showstandardinstruction>0</showstandardinstruction><correctfeedback format="html"><text><![CDATA[<p>Your answer is correct.</p>]]></text></correctfeedback><partiallycorrectfeedback format="html"><text><![CDATA[<p>Your answer is partially correct.</p>]]></text></partiallycorrectfeedback><incorrectfeedback format="html"><text><![CDATA[<p>Your answer is incorrect.</p>]]></text></incorrectfeedback><shownumcorrect/><answer fraction="0.0" format="html"><text><![CDATA[<p>AST</p>]]></text><feedback><text/></feedback></answer><answer fraction="0.0" format="html"><text><![CDATA[<p>CK</p>]]></text><feedback><text/></feedback></answer><answer fraction="0.0" format="html"><text><![CDATA[<p>LDH</p>]]></text><feedback><text/></feedback></answer><answer fraction="50.0" format="html"><text><![CDATA[<p>semua benar</p>]]></text><feedback><text/></feedback></answer></question><question type="multichoice"><name><text>Ujian Materi DKS 19 November 2021</text></name><questiontext format="html"><text><![CDATA[<p>Lactate Dehydrogenase (LDH) sebagai indikator kerusakan otot ditemukan juga pada</p>]]></text></questiontext><generalfeedback format="html"><text/></generalfeedback><defaultgrade>1</defaultgrade><penalty>0</penalty><hidden>0</hidden><idnumber>QST_154686</idnumber><single>true</single><answernumbering>abc</answernumbering><showstandardinstruction>0</showstandardinstruction><correctfeedback format="html"><text><![CDATA[<p>Your answer is correct.</p>]]></text></correctfeedback><partiallycorrectfeedback format="html"><text><![CDATA[<p>Your answer is partially correct.</p>]]></text></partiallycorrectfeedback><incorrectfeedback format="html"><text><![CDATA[<p>Your answer is incorrect.</p>]]></text></incorrectfeedback><shownumcorrect/><answer fraction="50.0" format="html"><text><![CDATA[<p>hati, jantung</p>]]></text><feedback><text/></feedback></answer><answer fraction="0.0" format="html"><text><![CDATA[<p>usus, lambung</p>]]></text><feedback><text/></feedback></answer><answer fraction="0.0" format="html"><text><![CDATA[<p>paru-paru</p>]]></text><feedback><text/></feedback></answer><answer fraction="0.0" format="html"><text><![CDATA[<p>ginjal</p>]]></text><feedback><text/></feedback></answer></question><question type="multichoice"><name><text>Ujian Materi DKS 19 November 2021</text></name><questiontext format="html"><text><![CDATA[<p>5 isoenzim LDH sebagai indikator kerusakan hati</p>]]></text></questiontext><generalfeedback format="html"><text/></generalfeedback><defaultgrade>1</defaultgrade><penalty>0</penalty><hidden>0</hidden><idnumber>QST_154690</idnumber><single>true</single><answernumbering>abc</answernumbering><showstandardinstruction>0</showstandardinstruction><correctfeedback format="html"><text><![CDATA[<p>Your answer is correct.</p>]]></text></correctfeedback><partiallycorrectfeedback format="html"><text><![CDATA[<p>Your answer is partially correct.</p>]]></text></partiallycorrectfeedback><incorrectfeedback format="html"><text><![CDATA[<p>Your answer is incorrect.</p>]]></text></incorrectfeedback><shownumcorrect/><answer fraction="0.0" format="html"><text><![CDATA[<p>M2H2</p>]]></text><feedback><text/></feedback></answer><answer fraction="0.0" format="html"><text><![CDATA[<p>M3H</p>]]></text><feedback><text/></feedback></answer><answer fraction="50.0" format="html"><text><![CDATA[<p>M4</p>]]></text><feedback><text/></feedback></answer><answer fraction="0.0" format="html"><text><![CDATA[<p>MH3</p>]]></text><feedback><text/></feedback></answer></question><question type="multichoice"><name><text>Ujian Materi DKS 19 November 2021</text></name><questiontext format="html"><text><![CDATA[<p>Indikator yang digunakan untuk melihat kerusakan otot adalah enzim?</p>]]></text></questiontext><generalfeedback format="html"><text/></generalfeedback><defaultgrade>1</defaultgrade><penalty>0</penalty><hidden>0</hidden><idnumber>QST_154693</idnumber><single>true</single><answernumbering>abc</answernumbering><showstandardinstruction>0</showstandardinstruction><correctfeedback format="html"><text><![CDATA[<p>Your answer is correct.</p>]]></text></correctfeedback><partiallycorrectfeedback format="html"><text><![CDATA[<p>Your answer is partially correct.</p>]]></text></partiallycorrectfeedback><incorrectfeedback format="html"><text><![CDATA[<p>Your answer is incorrect.</p>]]></text></incorrectfeedback><shownumcorrect/><answer fraction="50.0" format="html"><text><![CDATA[<p>CK</p>]]></text><feedback><text/></feedback></answer><answer fraction="0.0" format="html"><text><![CDATA[<p>LDH</p>]]></text><feedback><text/></feedback></answer><answer fraction="0.0" format="html"><text><![CDATA[<p>ALT</p>]]></text><feedback><text/></feedback></answer><answer fraction="0.0" format="html"><text><![CDATA[<p>cTN</p>]]></text><feedback><text/></feedback></answer></question><question type="multichoice"><name><text>Ujian Materi DKS 19 November 2021</text></name><questiontext format="html"><text><![CDATA[<p>Indikator untuk melihat kerusakan jantung</p>]]></text></questiontext><generalfeedback format="html"><text/></generalfeedback><defaultgrade>1</defaultgrade><penalty>0</penalty><hidden>0</hidden><idnumber>QST_154694</idnumber><single>true</single><answernumbering>abc</answernumbering><showstandardinstruction>0</showstandardinstruction><correctfeedback format="html"><text><![CDATA[<p>Your answer is correct.</p>]]></text></correctfeedback><partiallycorrectfeedback format="html"><text><![CDATA[<p>Your answer is partially correct.</p>]]></text></partiallycorrectfeedback><incorrectfeedback format="html"><text><![CDATA[<p>Your answer is incorrect.</p>]]></text></incorrectfeedback><shownumcorrect/><answer fraction="0.0" format="html"><text><![CDATA[<p>CK</p>]]></text><feedback><text/></feedback></answer><answer fraction="0.0" format="html"><text><![CDATA[<p>LDH</p>]]></text><feedback><text/></feedback></answer><answer fraction="0.0" format="html"><text><![CDATA[<p>ALT</p>]]></text><feedback><text/></feedback></answer><answer fraction="50.0" format="html"><text><![CDATA[<p>cTn</p>]]></text><feedback><text/></feedback></answer></question><question type="multichoice"><name><text>Ujian Materi DKS 19 November 2021</text></name><questiontext format="html"><text><![CDATA[<p>Penyebab peningkatan level CK</p>]]></text></questiontext><generalfeedback format="html"><text/></generalfeedback><defaultgrade>1</defaultgrade><penalty>0</penalty><hidden>0</hidden><idnumber>QST_154697</idnumber><single>true</single><answernumbering>abc</answernumbering><showstandardinstruction>0</showstandardinstruction><correctfeedback format="html"><text><![CDATA[<p>Your answer is correct.</p>]]></text></correctfeedback><partiallycorrectfeedback format="html"><text><![CDATA[<p>Your answer is partially correct.</p>]]></text></partiallycorrectfeedback><incorrectfeedback format="html"><text><![CDATA[<p>Your answer is incorrect.</p>]]></text></incorrectfeedback><shownumcorrect/><answer fraction="0.0" format="html"><text><![CDATA[<p>Artifact</p>]]></text><feedback><text/></feedback></answer><answer fraction="0.0" format="html"><text><![CDATA[<p>Fisiologi</p>]]></text><feedback><text/></feedback></answer><answer fraction="0.0" format="html"><text><![CDATA[<p>Injeksi IM</p>]]></text><feedback><text/></feedback></answer><answer fraction="100.0" format="html"><text><![CDATA[<p>Semua benar</p>]]></text><feedback><text/></feedback></answer></question><question type="multichoice"><name><text>Ujian Materi DKS 19 November 2021</text></name><questiontext format="html"><text><![CDATA[<p>Untuk mengetahui adanya gangguan di organ pancreas ada beberapa indikator yang harus dinilai dari pemeriksaan darah antara lain - Copy</p>]]></text></questiontext><generalfeedback format="html"><text/></generalfeedback><defaultgrade>1</defaultgrade><penalty>0</penalty><hidden>0</hidden><idnumber>QST_226269</idnumber><single>true</single><answernumbering>abc</answernumbering><showstandardinstruction>0</showstandardinstruction><correctfeedback format="html"><text><![CDATA[<p>Your answer is correct.</p>]]></text></correctfeedback><partiallycorrectfeedback format="html"><text><![CDATA[<p>Your answer is partially correct.</p>]]></text></partiallycorrectfeedback><incorrectfeedback format="html"><text><![CDATA[<p>Your answer is incorrect.</p>]]></text></incorrectfeedback><shownumcorrect/><answer fraction="0.0" format="html"><text><![CDATA[<p>Enzim lipase</p>]]></text><feedback><text/></feedback></answer><answer fraction="0.0" format="html"><text><![CDATA[<p>enzim amilase</p>]]></text><feedback><text/></feedback></answer><answer fraction="50.0" format="html"><text><![CDATA[<p>Enzim lipase dan amilase</p>]]></text><feedback><text/></feedback></answer><answer fraction="0.0" format="html"><text><![CDATA[<p>Enzim katalase</p>]]></text><feedback><text/></feedback></answer></question></quiz>