<?xml version='1.0' encoding='UTF-8'?>
<quiz><question type="essay"><name><text>Final GDH 1 - 2023 (Dosen : Dr.Abdul Salam)</text></name><questiontext format="html"><text><![CDATA[<p>1. Anemia pada ibu hamil menjadi salah satu persoalan gizi masyarakat di Indonesia, Jelaskan faktor apa saja yang dapat menyebabkan anemia pada ibu hamil dan berikan gambaran prevalensi anemia pada ibu hamil saat ini di Indonesia !</p>]]></text></questiontext><generalfeedback format="html"><text/></generalfeedback><defaultgrade>250.0</defaultgrade><penalty>0</penalty><hidden>0</hidden><idnumber>QST_57672</idnumber><responseformat>editor</responseformat><responserequired>1</responserequired><responsefieldlines>10</responsefieldlines><minwordlimit/><maxwordlimit/><attachments>0</attachments><attachmentsrequired>0</attachmentsrequired><maxbytes>0</maxbytes><filetypeslist/><graderinfo format="html"><text/></graderinfo><responsetemplate format="html"><text/></responsetemplate></question><question type="essay"><name><text>Final GDH 1 - 2023 (Dosen : Dr.Abdul Salam)</text></name><questiontext format="html"><text><![CDATA[<p>2. Salah satu indikator untuk melihat tingkat kesejahteraan masyarakat disuatu wilayah adalah mengukur Angka Kematian ibu, jelaskan apa yang dimaksud dengan angka kematian ibu ? berapa kisaran target penurunan AKI pada tahun 2024 ?  </p>]]></text></questiontext><generalfeedback format="html"><text/></generalfeedback><defaultgrade>250.0</defaultgrade><penalty>0</penalty><hidden>0</hidden><idnumber>QST_57673</idnumber><responseformat>editor</responseformat><responserequired>1</responserequired><responsefieldlines>10</responsefieldlines><minwordlimit/><maxwordlimit/><attachments>0</attachments><attachmentsrequired>0</attachmentsrequired><maxbytes>0</maxbytes><filetypeslist/><graderinfo format="html"><text/></graderinfo><responsetemplate format="html"><text/></responsetemplate></question><question type="essay"><name><text>Final GDH 1 - 2023 (Dosen : Dr.Abdul Salam)</text></name><questiontext format="html"><text><![CDATA[<p>3. Dalam framework WHO tentang faktor-faktor yang berpengaruh terhadap perkembangan masalah stunting atau masalah gizi pada anak balita, salah satunya adalah adanya poor quality of foods, jelaskan apa saja yang termasuk di dalam komponen poor quality of foods tersebut !</p>]]></text></questiontext><generalfeedback format="html"><text/></generalfeedback><defaultgrade>250.0</defaultgrade><penalty>0</penalty><hidden>0</hidden><idnumber>QST_57674</idnumber><responseformat>editor</responseformat><responserequired>1</responserequired><responsefieldlines>10</responsefieldlines><minwordlimit/><maxwordlimit/><attachments>0</attachments><attachmentsrequired>0</attachmentsrequired><maxbytes>0</maxbytes><filetypeslist/><graderinfo format="html"><text/></graderinfo><responsetemplate format="html"><text/></responsetemplate></question><question type="essay"><name><text>Final GDH 1 - 2023 (Dosen : Dr.Abdul Salam)</text></name><questiontext format="html"><text><![CDATA[<p>4. Dalam kerangka penyebab stunting di Indonesia, terdapat dua penyebab yakni penyebab langsung dan penyebab tidak langsung. Jelaskan apa yang termasuk dalam penyebab langsung dan penyebab tidak langsung !</p>]]></text></questiontext><generalfeedback format="html"><text/></generalfeedback><defaultgrade>250.0</defaultgrade><penalty>0</penalty><hidden>0</hidden><idnumber>QST_57676</idnumber><responseformat>editor</responseformat><responserequired>1</responserequired><responsefieldlines>10</responsefieldlines><minwordlimit/><maxwordlimit/><attachments>0</attachments><attachmentsrequired>0</attachmentsrequired><maxbytes>0</maxbytes><filetypeslist/><graderinfo format="html"><text/></graderinfo><responsetemplate format="html"><text/></responsetemplate></question></quiz>