<?xml version='1.0' encoding='UTF-8'?>
<quiz><question type="multichoice"><name><text>Tes Formatif II-V</text></name><questiontext format="html"><text><![CDATA[<p>Klausula Ketentuan-ketentuan Umum dalam kontrak bisnis biasanya terdiri dari...</p>]]></text></questiontext><generalfeedback format="html"><text/></generalfeedback><defaultgrade>1</defaultgrade><penalty>0</penalty><hidden>0</hidden><idnumber>QST_36216</idnumber><single>false</single><answernumbering>abc</answernumbering><showstandardinstruction>0</showstandardinstruction><correctfeedback><text><![CDATA[<p>Your answer is correct.</p>]]></text></correctfeedback><partiallycorrectfeedback><text><![CDATA[<p>Your answer is partially correct.</p>]]></text></partiallycorrectfeedback><incorrectfeedback><text><![CDATA[<p>Your answer is incorrect.</p>]]></text></incorrectfeedback><shownumcorrect/><answer fraction="0.0" format="html"><text><![CDATA[domisili hukum]]></text><feedback><text/></feedback></answer><answer fraction="0.0" format="html"><text><![CDATA[pengakhiran kontrak]]></text><feedback><text/></feedback></answer><answer fraction="0.0" format="html"><text><![CDATA[keterpisahan]]></text><feedback><text/></feedback></answer><answer fraction="100.0" format="html"><text><![CDATA[semua jawaban benar]]></text><feedback><text/></feedback></answer></question><question type="multichoice"><name><text>Tes Formatif II-V</text></name><questiontext format="html"><text><![CDATA[<p>Klausula Spesifik dalam kontrak bisnis berkaitan dengan...</p>]]></text></questiontext><generalfeedback format="html"><text/></generalfeedback><defaultgrade>1</defaultgrade><penalty>0</penalty><hidden>0</hidden><idnumber>QST_36218</idnumber><single>false</single><answernumbering>abc</answernumbering><showstandardinstruction>0</showstandardinstruction><correctfeedback><text><![CDATA[<p>Your answer is correct.</p>]]></text></correctfeedback><partiallycorrectfeedback><text><![CDATA[<p>Your answer is partially correct.</p>]]></text></partiallycorrectfeedback><incorrectfeedback><text><![CDATA[<p>Your answer is incorrect.</p>]]></text></incorrectfeedback><shownumcorrect/><answer fraction="0.0" format="html"><text><![CDATA[semua transaksi]]></text><feedback><text/></feedback></answer><answer fraction="100.0" format="html"><text><![CDATA[transaksi tertentu]]></text><feedback><text/></feedback></answer><answer fraction="0.0" format="html"><text><![CDATA[transaksi bisnis]]></text><feedback><text/></feedback></answer><answer fraction="0.0" format="html"><text><![CDATA[semua jawaban salah]]></text><feedback><text/></feedback></answer></question><question type="multichoice"><name><text>Tes Formatif II-V</text></name><questiontext format="html"><text><![CDATA[<p>Dalam merancang suatu kontrak dapat dibuat secara bebas, kecuali telah diatur dalam Undang-undang.</p>]]></text></questiontext><generalfeedback format="html"><text/></generalfeedback><defaultgrade>1</defaultgrade><penalty>0</penalty><hidden>0</hidden><idnumber>QST_36219</idnumber><single>true</single><answernumbering>abc</answernumbering><showstandardinstruction>0</showstandardinstruction><correctfeedback format="html"><text><![CDATA[<p>Your answer is correct.</p>]]></text></correctfeedback><partiallycorrectfeedback format="html"><text><![CDATA[<p>Your answer is partially correct.</p>]]></text></partiallycorrectfeedback><incorrectfeedback format="html"><text><![CDATA[<p>Your answer is incorrect.</p>]]></text></incorrectfeedback><shownumcorrect/><answer fraction="100.0" format="html"><text><![CDATA[<p>Benar</p>]]></text><feedback><text/></feedback></answer><answer fraction="0.0" format="html"><text><![CDATA[<p>Salah</p>]]></text><feedback><text/></feedback></answer></question><question type="multichoice"><name><text>Tes Formatif II-V</text></name><questiontext format="html"><text><![CDATA[<p>Akibat hukum dari debitur yang telah melakukan wan prestasi  adalah hukuman atau sanksi berupa dibebaskan  membayar  kerugian kepada kreditur.</p>]]></text></questiontext><generalfeedback format="html"><text/></generalfeedback><defaultgrade>1</defaultgrade><penalty>0</penalty><hidden>0</hidden><idnumber>QST_36220</idnumber><single>false</single><answernumbering>abc</answernumbering><showstandardinstruction>0</showstandardinstruction><correctfeedback><text><![CDATA[<p>Your answer is correct.</p>]]></text></correctfeedback><partiallycorrectfeedback><text><![CDATA[<p>Your answer is partially correct.</p>]]></text></partiallycorrectfeedback><incorrectfeedback><text><![CDATA[<p>Your answer is incorrect.</p>]]></text></incorrectfeedback><shownumcorrect/><answer fraction="0.0" format="html"><text><![CDATA[benar]]></text><feedback><text/></feedback></answer><answer fraction="100.0" format="html"><text><![CDATA[salah]]></text><feedback><text/></feedback></answer></question><question type="multichoice"><name><text>Tes Formatif II-V</text></name><questiontext format="html"><text><![CDATA[<p>Penyelesaian sengketa  dalam suatu kontrak harus dimasukkan dalam   klausul kontrak  apabila salah satu pihak wanprestasi</p>]]></text></questiontext><generalfeedback format="html"><text/></generalfeedback><defaultgrade>1</defaultgrade><penalty>0</penalty><hidden>0</hidden><idnumber>QST_36221</idnumber><single>false</single><answernumbering>abc</answernumbering><showstandardinstruction>0</showstandardinstruction><correctfeedback><text><![CDATA[<p>Your answer is correct.</p>]]></text></correctfeedback><partiallycorrectfeedback><text><![CDATA[<p>Your answer is partially correct.</p>]]></text></partiallycorrectfeedback><incorrectfeedback><text><![CDATA[<p>Your answer is incorrect.</p>]]></text></incorrectfeedback><shownumcorrect/><answer fraction="100.0" format="html"><text><![CDATA[benar]]></text><feedback><text/></feedback></answer><answer fraction="0.0" format="html"><text><![CDATA[salah]]></text><feedback><text/></feedback></answer></question><question type="multichoice"><name><text>Tes Formatif II-V</text></name><questiontext format="html"><text><![CDATA[<p>Dalam perjanjian atau kontrak tanda tangan tidak difungsikan untuk menjamin bahwa  benar orang yang menandatangani perjanjian atau kontrak telah mengetahui  dan menyetujui seluruh isinya</p>]]></text></questiontext><generalfeedback format="html"><text/></generalfeedback><defaultgrade>1</defaultgrade><penalty>0</penalty><hidden>0</hidden><idnumber>QST_36222</idnumber><single>false</single><answernumbering>abc</answernumbering><showstandardinstruction>0</showstandardinstruction><correctfeedback><text><![CDATA[<p>Your answer is correct.</p>]]></text></correctfeedback><partiallycorrectfeedback><text><![CDATA[<p>Your answer is partially correct.</p>]]></text></partiallycorrectfeedback><incorrectfeedback><text><![CDATA[<p>Your answer is incorrect.</p>]]></text></incorrectfeedback><shownumcorrect/><answer fraction="0.0" format="html"><text><![CDATA[benar]]></text><feedback><text/></feedback></answer><answer fraction="100.0" format="html"><text><![CDATA[salah]]></text><feedback><text/></feedback></answer></question><question type="multichoice"><name><text>Tes Formatif II-V</text></name><questiontext format="html"><text><![CDATA[<p>Ada tiga cara terjadinya somasi: - Debitor melaksanakan prestasi yang keliru - Debitor tidak memenuhi prestasi pada hari yang telah dijanjikan. - Prestasi yang dilaksanakan oleh debitor tidak lagi berguna bagi kreditor setelah lewat waktu yang diperjanjikan</p>]]></text></questiontext><generalfeedback format="html"><text/></generalfeedback><defaultgrade>1</defaultgrade><penalty>0</penalty><hidden>0</hidden><idnumber>QST_36224</idnumber><single>false</single><answernumbering>abc</answernumbering><showstandardinstruction>0</showstandardinstruction><correctfeedback><text><![CDATA[<p>Your answer is correct.</p>]]></text></correctfeedback><partiallycorrectfeedback><text><![CDATA[<p>Your answer is partially correct.</p>]]></text></partiallycorrectfeedback><incorrectfeedback><text><![CDATA[<p>Your answer is incorrect.</p>]]></text></incorrectfeedback><shownumcorrect/><answer fraction="100.0" format="html"><text><![CDATA[Benar]]></text><feedback><text/></feedback></answer><answer fraction="0.0" format="html"><text><![CDATA[Salah]]></text><feedback><text/></feedback></answer></question><question type="multichoice"><name><text>Tes Formatif II-V</text></name><questiontext format="html"><text><![CDATA[<p>Klausula transaksi dalam suatu kontrak berkaitan dengan unsur perjanjian, yaitu:</p>]]></text></questiontext><generalfeedback format="html"><text/></generalfeedback><defaultgrade>1</defaultgrade><penalty>0</penalty><hidden>0</hidden><idnumber>QST_36380</idnumber><single>false</single><answernumbering>abc</answernumbering><showstandardinstruction>0</showstandardinstruction><correctfeedback><text><![CDATA[<p>Your answer is correct.</p>]]></text></correctfeedback><partiallycorrectfeedback><text><![CDATA[<p>Your answer is partially correct.</p>]]></text></partiallycorrectfeedback><incorrectfeedback><text><![CDATA[<p>Your answer is incorrect.</p>]]></text></incorrectfeedback><shownumcorrect/><answer fraction="0.0" format="html"><text><![CDATA[unsur naturalia]]></text><feedback><text/></feedback></answer><answer fraction="0.0" format="html"><text><![CDATA[unsur aksidentalia]]></text><feedback><text/></feedback></answer><answer fraction="0.0" format="html"><text><![CDATA[unsur para pihak]]></text><feedback><text/></feedback></answer><answer fraction="100.0" format="html"><text><![CDATA[unsur esensilia]]></text><feedback><text/></feedback></answer></question></quiz>