<?xml version='1.0' encoding='UTF-8'?>
<quiz><question type="multichoice"><name><text>Kuis 1</text></name><questiontext format="html"><text><![CDATA[<p>Apakah yang dimaksudkan dengan persamaan differential</p>]]></text></questiontext><generalfeedback format="html"><text/></generalfeedback><defaultgrade>1</defaultgrade><penalty>0</penalty><hidden>0</hidden><idnumber>QST_25653</idnumber><single>true</single><answernumbering>abc</answernumbering><showstandardinstruction>0</showstandardinstruction><correctfeedback format="html"><text><![CDATA[<p>Your answer is correct.</p>]]></text></correctfeedback><partiallycorrectfeedback format="html"><text><![CDATA[<p>Your answer is partially correct.</p>]]></text></partiallycorrectfeedback><incorrectfeedback format="html"><text><![CDATA[<p>Your answer is incorrect.</p>]]></text></incorrectfeedback><shownumcorrect/><answer fraction="0.0" format="html"><text><![CDATA[<p>A</p>]]></text><feedback><text/></feedback></answer><answer fraction="0.0" format="html"><text><![CDATA[<p>B </p>]]></text><feedback><text/></feedback></answer><answer fraction="0.0" format="html"><text><![CDATA[<p>V</p>]]></text><feedback><text/></feedback></answer><answer fraction="0.0" format="html"><text><![CDATA[<p>D</p>]]></text><feedback><text/></feedback></answer></question></quiz>