{
  "id_prodi": 21,
  "nama_prodi": "TEKNIK GEOLOGI - S1",
  "id_prodi_semester": 2386,
  "idnumber_sikola": "47936.115434.21",
  "shortname_sikola": "TA231-115434",
  "kode_matkul": "23D06121503",
  "nama_matkul": "Mineral Optik dan Petrografi",
  "nama_kelas": "Mineral Optik dan Petrogfafi",
  "mahasiswas": [
    {
      "deleted_at": null,
      "id": 39682,
      "id_user": 5551,
      "id_prodi": 21,
      "angkatan": 2019,
      "nama_mahasiswa": "RIZKY ANANDA IDSAM",
      "nim": "D061191021",
      "jalan": "Jl. Kebantenan No.20",
      "rt": 2,
      "rw": 2,
      "dusun": "Gg. merpati",
      "kode_pos": "14130",
      "nisn": "0012933053",
      "tempat_lahir": "jakarta",
      "tanggal_lahir": "2001-06-20",
      "telepon": "081211417545",
      "handphone": "6281211417545",
      "id_agama": null,
      "id_prodi_jenjang": 1,
      "kelurahan": "Semper Timur",
      "id_wilayah": "016106",
      "nik": "3172042006010006",
      "jenis_kelamin": "L",
      "is_active": 1,
      "updated_by": 1,
      "kode_status": "A",
      "email": "rizky8771@gmail.com",
      "is_tamu": 0,
      "id_mahasiswa_pddikti": "b573b9d5-5ca0-4364-afef-72baefc4d09e",
      "id_registrasi_mahasiswa_pddikti": "6c38c419-5b39-47e2-a4c4-28ca1d0a9ccc",
      "spp": null,
      "whatsapp": null,
      "pivot": {
        "id_kelas_kuliah": 115434,
        "id_mahasiswa": 39682,
        "created_at": "2023-08-13 19:17:45"
      }
    },
    {
      "deleted_at": null,
      "id": 39676,
      "id_user": 5533,
      "id_prodi": 21,
      "angkatan": 2019,
      "nama_mahasiswa": "Ruzik Wirdando Musfa",
      "nim": "D061191012",
      "jalan": "Perum Griya Manggala Sejahtera No.5",
      "rt": 1,
      "rw": 5,
      "dusun": "Bangkala",
      "kode_pos": "92984",
      "nisn": "0018055736",
      "tempat_lahir": "Sorowako",
      "tanggal_lahir": "2001-06-16",
      "telepon": "0811425914",
      "handphone": "6282296245954",
      "id_agama": null,
      "id_prodi_jenjang": 1,
      "kelurahan": "Bangkala",
      "id_wilayah": "190000",
      "nik": "7324021606010001",
      "jenis_kelamin": "L",
      "is_active": 1,
      "updated_by": 1,
      "kode_status": "A",
      "email": "ruzikwirdando01@gmail.com",
      "is_tamu": 0,
      "id_mahasiswa_pddikti": "7d78d694-3721-4056-94a6-16a3692f2622",
      "id_registrasi_mahasiswa_pddikti": "ad37bbe4-c7ca-42a7-81b7-28c6728e1f89",
      "spp": null,
      "whatsapp": null,
      "pivot": {
        "id_kelas_kuliah": 115434,
        "id_mahasiswa": 39676,
        "created_at": "2023-08-13 19:19:49"
      }
    },
    {
      "deleted_at": null,
      "id": 39678,
      "id_user": 15648,
      "id_prodi": 21,
      "angkatan": 2019,
      "nama_mahasiswa": "Muh. Dani Ramadhan Prayitno",
      "nim": "D061191014",
      "jalan": "komp permata cinere 2 no.N-01,Kota Depok",
      "rt": 7,
      "rw": 7,
      "dusun": "Meruyung",
      "kode_pos": "16532",
      "nisn": "161707006",
      "tempat_lahir": "Makassar",
      "tanggal_lahir": "2000-11-08",
      "telepon": "08111991040",
      "handphone": "6281297278187",
      "id_agama": null,
      "id_prodi_jenjang": 1,
      "kelurahan": "Meruyung",
      "id_wilayah": "020000",
      "nik": "3276040811000004",
      "jenis_kelamin": "L",
      "is_active": 1,
      "updated_by": 1,
      "kode_status": "A",
      "email": "mdani081100@gmail.com",
      "is_tamu": 0,
      "id_mahasiswa_pddikti": "fe42860b-ea21-4c51-941c-7dba1cd47d2c",
      "id_registrasi_mahasiswa_pddikti": "3cb8650d-c462-4c08-8a78-20d08720e85d",
      "spp": null,
      "whatsapp": null,
      "pivot": {
        "id_kelas_kuliah": 115434,
        "id_mahasiswa": 39678,
        "created_at": "2023-08-13 19:24:45"
      }
    },
    {
      "deleted_at": null,
      "id": 39731,
      "id_user": 7533,
      "id_prodi": 21,
      "angkatan": 2019,
      "nama_mahasiswa": "Maxi William Lakaba",
      "nim": "D061191098",
      "jalan": "BTN Griya Seruni Permai B.19",
      "rt": 2,
      "rw": 3,
      "dusun": null,
      "kode_pos": "90245",
      "nisn": "0012536392",
      "tempat_lahir": "Mataram",
      "tanggal_lahir": "2001-08-05",
      "telepon": "0",
      "handphone": "6282236689881",
      "id_agama": null,
      "id_prodi_jenjang": 1,
      "kelurahan": "Taman Sari",
      "id_wilayah": "236001",
      "nik": "5271010508010004",
      "jenis_kelamin": "L",
      "is_active": 1,
      "updated_by": 1,
      "kode_status": "A",
      "email": "maxilakaba10@gmail.com",
      "is_tamu": 0,
      "id_mahasiswa_pddikti": "4e2b26e5-ce3b-43ac-aa53-39350a5b9194",
      "id_registrasi_mahasiswa_pddikti": "089f4f74-24bc-42a6-8897-db9e22ff038b",
      "spp": null,
      "whatsapp": null,
      "pivot": {
        "id_kelas_kuliah": 115434,
        "id_mahasiswa": 39731,
        "created_at": "2023-08-14 10:44:11"
      }
    },
    {
      "deleted_at": null,
      "id": 39720,
      "id_user": 13319,
      "id_prodi": 21,
      "angkatan": 2019,
      "nama_mahasiswa": "Raihan Ramadhani",
      "nim": "D061191078",
      "jalan": "Perum. cakalang mas A12",
      "rt": 3,
      "rw": 2,
      "dusun": "tidak ada",
      "kode_pos": "91921",
      "nisn": "0003217788",
      "tempat_lahir": "palopo",
      "tanggal_lahir": "2000-12-11",
      "telepon": "0",
      "handphone": "6282351000369",
      "id_agama": null,
      "id_prodi_jenjang": 1,
      "kelurahan": "surutanga",
      "id_wilayah": "190000",
      "nik": "7373051112000001",
      "jenis_kelamin": "L",
      "is_active": 1,
      "updated_by": 1,
      "kode_status": "A",
      "email": "rayhanramadhannn1@gmail.com",
      "is_tamu": 0,
      "id_mahasiswa_pddikti": "8ce982f8-364a-46ac-9c39-b78eb308da88",
      "id_registrasi_mahasiswa_pddikti": "77dec2ca-834c-4eb3-9f0e-c95d08f0cb52",
      "spp": null,
      "whatsapp": null,
      "pivot": {
        "id_kelas_kuliah": 115434,
        "id_mahasiswa": 39720,
        "created_at": "2023-08-14 10:45:04"
      }
    },
    {
      "deleted_at": null,
      "id": 39701,
      "id_user": 5541,
      "id_prodi": 21,
      "angkatan": 2019,
      "nama_mahasiswa": "Muhammad Syarief Prananta",
      "nim": "D061191051",
      "jalan": "Jalan Kebon Manggis II/C No.182A Rt.005 Rw.02",
      "rt": 5,
      "rw": 2,
      "dusun": "Kebon manggis",
      "kode_pos": "13150",
      "nisn": "0012028738",
      "tempat_lahir": "Jakarta",
      "tanggal_lahir": "2001-02-01",
      "telepon": "0",
      "handphone": "6281317971257",
      "id_agama": null,
      "id_prodi_jenjang": 1,
      "kelurahan": "Kebon manggis",
      "id_wilayah": "016410",
      "nik": "3175010102010003",
      "jenis_kelamin": "L",
      "is_active": 1,
      "updated_by": 1,
      "kode_status": "A",
      "email": "nantasteam@gmail.com",
      "is_tamu": 0,
      "id_mahasiswa_pddikti": "0676c459-841e-4c09-a058-78ff6048a325",
      "id_registrasi_mahasiswa_pddikti": "02489145-5791-4fb2-bda0-62358c03c156",
      "spp": null,
      "whatsapp": null,
      "pivot": {
        "id_kelas_kuliah": 115434,
        "id_mahasiswa": 39701,
        "created_at": "2023-08-14 10:47:06"
      }
    },
    {
      "deleted_at": null,
      "id": 39742,
      "id_user": 9982,
      "id_prodi": 21,
      "angkatan": 2019,
      "nama_mahasiswa": "MUH. RAFLI DWI ANUGRAH SAMSIR",
      "nim": "D061191112",
      "jalan": "GG.HIKMAH B NO.8",
      "rt": 3,
      "rw": 0,
      "dusun": null,
      "kode_pos": "75611",
      "nisn": "0",
      "tempat_lahir": "Palopo",
      "tanggal_lahir": "2000-11-05",
      "telepon": "0",
      "handphone": "089510637325",
      "id_agama": null,
      "id_prodi_jenjang": 1,
      "kelurahan": "Teluk Lingga",
      "id_wilayah": "191817",
      "nik": "6408040511000001",
      "jenis_kelamin": "L",
      "is_active": 1,
      "updated_by": 9982,
      "kode_status": "A",
      "email": "m.raflimuhammad05@gmail.com",
      "is_tamu": 0,
      "id_mahasiswa_pddikti": "962dad74-bf80-4516-acff-898538caa2b3",
      "id_registrasi_mahasiswa_pddikti": "a79618cf-4da6-460d-8931-bdbecdad5eb1",
      "spp": null,
      "whatsapp": null,
      "pivot": {
        "id_kelas_kuliah": 115434,
        "id_mahasiswa": 39742,
        "created_at": "2023-08-23 13:57:27"
      }
    }
  ],
  "dosens": [
    {
      "deleted_at": null,
      "id": 876,
      "id_user": 10614,
      "id_prodi": 21,
      "nama": "Dr. Ir.  Hamid Umar, MS.",
      "nidn": "0002116002",
      "nip": "196012021988111001",
      "is_active": 1,
      "updated_by": null,
      "id_registrasi_pddikti": "11bdd910-f86f-4005-9156-36953221304f",
      "pivot": {
        "id_kelas_kuliah": 115434,
        "id_dosen": 876
      }
    },
    {
      "deleted_at": null,
      "id": 1268,
      "id_user": 11723,
      "id_prodi": 21,
      "nama": "Dr. Ulva Ria Irvan, ST., MT.",
      "nidn": "0006067001",
      "nip": "197006061994122001",
      "is_active": 1,
      "updated_by": null,
      "id_registrasi_pddikti": "c783f066-8d13-4082-985a-ebc3ce227a5f",
      "pivot": {
        "id_kelas_kuliah": 115434,
        "id_dosen": 1268
      }
    },
    {
      "deleted_at": null,
      "id": 806,
      "id_user": 13031,
      "id_prodi": 21,
      "nama": "Dr. Ir. Kaharuddin, M.T.",
      "nidn": "8997370023",
      "nip": "195604211986091001",
      "is_active": 1,
      "updated_by": null,
      "id_registrasi_pddikti": "b1f22e87-63b5-437a-8dc9-18c277a473c0",
      "pivot": {
        "id_kelas_kuliah": 115434,
        "id_dosen": 806
      }
    }
  ]
}