{
  "id_prodi": 26,
  "nama_prodi": "ILMU HUB. INTERNASIONAL - S1",
  "id_prodi_semester": 2390,
  "idnumber_sikola": "45632.116150.26",
  "shortname_sikola": "TA231-116150",
  "kode_matkul": "23E04110102",
  "nama_matkul": "Pengantar Ilmu Politik",
  "nama_kelas": "Pengantar Ilmu Politik - C",
  "mahasiswas": [
    {
      "deleted_at": null,
      "id": 417028,
      "id_user": 83764,
      "id_prodi": 26,
      "angkatan": 2023,
      "nama_mahasiswa": "ANDI AUDIYA APRILIA",
      "nim": "E061231017",
      "jalan": "JL. GOARIA KOMP. BUMI PERMATA SUDIANG 2 BLOK B1/24",
      "rt": 5,
      "rw": 11,
      "dusun": "-",
      "kode_pos": "90242",
      "nisn": "0057017574",
      "tempat_lahir": "MAKASSAR",
      "tanggal_lahir": "2005-04-02",
      "telepon": "04114833085",
      "handphone": "081242933013",
      "id_agama": null,
      "id_prodi_jenjang": 1,
      "kelurahan": "Laikang",
      "id_wilayah": "196011",
      "nik": "7371144204050001",
      "jenis_kelamin": "P",
      "is_active": 1,
      "updated_by": 1,
      "kode_status": "A",
      "email": "odiips@gmail.com",
      "is_tamu": 0,
      "id_mahasiswa_pddikti": "d0b7209b-4d9e-4842-953e-c8f2e5d002e2",
      "id_registrasi_mahasiswa_pddikti": "629174d1-8384-41b8-9fd9-342122d2563b",
      "spp": null,
      "whatsapp": null,
      "pivot": {
        "id_kelas_kuliah": 116150,
        "id_mahasiswa": 417028,
        "created_at": "2023-08-20 15:54:51"
      }
    },
    {
      "deleted_at": null,
      "id": 417031,
      "id_user": 84569,
      "id_prodi": 26,
      "angkatan": 2023,
      "nama_mahasiswa": "LUTFIYAH AL HUMAIRAH",
      "nim": "E061231020",
      "jalan": "JL. C H MARTHATIAHAHU",
      "rt": 1,
      "rw": 1,
      "dusun": null,
      "kode_pos": "98818",
      "nisn": "0052390384",
      "tempat_lahir": "NABIRE",
      "tanggal_lahir": "2005-12-01",
      "telepon": "0",
      "handphone": "081357150419",
      "id_agama": null,
      "id_prodi_jenjang": 1,
      "kelurahan": "Kalibobo",
      "id_wilayah": "250908",
      "nik": "9104014112050002",
      "jenis_kelamin": "P",
      "is_active": 1,
      "updated_by": 1,
      "kode_status": "A",
      "email": "humairahlutfiyah@gmail.com",
      "is_tamu": 0,
      "id_mahasiswa_pddikti": "225a3b6b-082f-4af0-85fb-1012bb29941b",
      "id_registrasi_mahasiswa_pddikti": "a5d440b8-72d2-42d1-9085-63b1e3b61be1",
      "spp": null,
      "whatsapp": null,
      "pivot": {
        "id_kelas_kuliah": 116150,
        "id_mahasiswa": 417031,
        "created_at": "2023-08-20 16:12:00"
      }
    },
    {
      "deleted_at": null,
      "id": 417036,
      "id_user": 81110,
      "id_prodi": 26,
      "angkatan": 2023,
      "nama_mahasiswa": "IMANUEL TODING BUA",
      "nim": "E061231025",
      "jalan": "JALAN SERANG",
      "rt": 7,
      "rw": 4,
      "dusun": "-",
      "kode_pos": "91834",
      "nisn": "0060171986",
      "tempat_lahir": "TANA TORAJA",
      "tanggal_lahir": "2006-03-04",
      "telepon": "0",
      "handphone": "0895360699832",
      "id_agama": null,
      "id_prodi_jenjang": 1,
      "kelurahan": "mentirotiku",
      "id_wilayah": "192710",
      "nik": "7326200403060002",
      "jenis_kelamin": "L",
      "is_active": 1,
      "updated_by": 1,
      "kode_status": "A",
      "email": "imanueltodingbua3@gmail.com",
      "is_tamu": 0,
      "id_mahasiswa_pddikti": "a4adc693-967c-4c6d-bae6-74f97f411091",
      "id_registrasi_mahasiswa_pddikti": "7554bd68-a834-43f1-90f0-fdbec040252f",
      "spp": null,
      "whatsapp": null,
      "pivot": {
        "id_kelas_kuliah": 116150,
        "id_mahasiswa": 417036,
        "created_at": "2023-08-21 15:40:50"
      }
    }
  ],
  "dosens": []
}